Metadata-Version: 2.4
Name: bus-mgmt-mcp-server
Version: 0.1.14
Summary: Bus Management MCP Server
Requires-Python: >=3.11
Requires-Dist: fastmcp
